YolikLogging/__init__.py
YolikLogging/yolikLog.py
YolikLogging-0.0.2.dist-info/METADATA
YolikLogging-0.0.2.dist-info/WHEEL
YolikLogging-0.0.2.dist-info/top_level.txt
YolikLogging-0.0.2.dist-info/RECORD
